orilinx/__init__.py
orilinx/__main__.py
orilinx/cli.py
orilinx/data.py
orilinx/io.py
orilinx/model_architecture.py
orilinx/utils.py
orilinx-1.0.1.dist-info/METADATA
orilinx-1.0.1.dist-info/WHEEL
orilinx-1.0.1.dist-info/entry_points.txt
orilinx-1.0.1.dist-info/top_level.txt
orilinx-1.0.1.dist-info/RECORD
