Metadata-Version: 2.4
Name: orilinx
Version: 1.0.1
Summary: Genome-wide origin scoring with DNABERT-2
Requires-Python: >=3.9
Requires-Dist: torch==2.6.0
Requires-Dist: transformers==4.57.5
Requires-Dist: pysam>=0.23.0
Requires-Dist: pandas>=2.0.0
Requires-Dist: numpy>=1.20.0
Requires-Dist: einops>=0.8.0
Requires-Dist: peft>=0.15.0
Requires-Dist: accelerate>=1.10.0
Requires-Dist: protobuf>=3.20.0
